subgapfix/__init__.py
subgapfix/subgapfix.py
subgapfix-0.0.2.dist-info/METADATA
subgapfix-0.0.2.dist-info/WHEEL
subgapfix-0.0.2.dist-info/entry_points.txt
subgapfix-0.0.2.dist-info/top_level.txt
subgapfix-0.0.2.dist-info/RECORD
