Metadata-Version: 2.4
Name: subgapfix
Version: 0.0.2
Summary: A small CLI tool to extend subtitle durations in SRT files by redefining gaps between subtitles.
Author-email: Reinder Sinnema <reinder@w3bunker.com>
License: MIT
Requires-Python: >=3.8
Requires-Dist: srt>=3.5.3
